github_avatars_gallery_generator/__init__.py
github_avatars_gallery_generator/main.py
github_avatars_gallery_generator-0.2.0.dist-info/entry_points.txt
github_avatars_gallery_generator-0.2.0.dist-info/LICENSE
github_avatars_gallery_generator-0.2.0.dist-info/WHEEL
github_avatars_gallery_generator-0.2.0.dist-info/METADATA
github_avatars_gallery_generator-0.2.0.dist-info/RECORD
